{
  "date_bulletin": "Bulletin du 1er Mai 2024 à 12h00_page1_map2",
  "map_type": "forecast",
  "source_image": "Bulletin du 1er Mai 2024 à 12h00_page1_map2.png",
  "stations": [
    {
      "nom": "GAOUA",
      "tmin": 29,
      "tmax": 41
    },
    {
      "nom": "BANFORA",
      "tmin": null,
      "tmax": null
    },
    {
      "nom": "BOBO DIOULASSO",
      "tmin": 28,
      "tmax": 40
    },
    {
      "nom": "PO",
      "tmin": 29,
      "tmax": 43
    },
    {
      "nom": "LEO",
      "tmin": null,
      "tmax": null
    },
    {
      "nom": "BOROMO",
      "tmin": 31,
      "tmax": 42
    },
    {
      "nom": "DEDOUGOU",
      "tmin": 30,
      "tmax": 42
    },
    {
      "nom": "OUAGADOUGOU",
      "tmin": 31,
      "tmax": 42
    },
    {
      "nom": "TENKODOGO",
      "tmin": null,
      "tmax": null
    },
    {
      "nom": "FADA NGOURMA",
      "tmin": 31,
      "tmax": 44
    },
    {
      "nom": "DIAPAGA",
      "tmin": 25,
      "tmax": 39
    },
    {
      "nom": "BOGANDE",
      "tmin": 31,
      "tmax": 44
    },
    {
      "nom": "DORI",
      "tmin": 28,
      "tmax": 44
    },
    {
      "nom": "DJIBO",
      "tmin": null,
      "tmax": null
    },
    {
      "nom": "GOROM GOROM",
      "tmin": null,
      "tmax": null
    },
    {
      "nom": "OUAHIGOUYA",
      "tmin": 31,
      "tmax": 42
    },
    {
      "nom": "KOUDOUGOU",
      "tmin": null,
      "tmax": null
    },
    {
      "nom": "KAYA",
      "tmin": null,
      "tmax": null
    },
    {
      "nom": "TOUGAN",
      "tmin": null,
      "tmax": null
    },
    {
      "nom": "MANGA",
      "tmin": null,
      "tmax": null
    }
  ]
}